socialist_core_values/__init__.py
socialist_core_values/main.py
socialist_core_values-2.0.dist-info/LICENSE
socialist_core_values-2.0.dist-info/METADATA
socialist_core_values-2.0.dist-info/WHEEL
socialist_core_values-2.0.dist-info/top_level.txt
socialist_core_values-2.0.dist-info/RECORD
