Metadata-Version: 2.1
Name: socialist-core-values
Version: 2.0
Summary: 社会主义核心价值观加解密
Home-page: https://github.com/langsasec/socialist_core_values
Author: 浪飒
Author-email: langsa-hy@qq.com
License: GPL
License-File: LICENSE
